iaa_seminario1/__main__.py
iaa_seminario1/license/__init__.py
iaa_seminario1-0.1.0.dist-info/METADATA
iaa_seminario1-0.1.0.dist-info/WHEEL
iaa_seminario1-0.1.0.dist-info/entry_points.txt
iaa_seminario1-0.1.0.dist-info/RECORD
