Metadata-Version: 2.1
Name: iaa-seminario1
Version: 0.1.0
Summary: Using bayesian networks for just about everything
Author: Pablo Hernández
Author-email: 17086478+Hadronomy@users.noreply.github.com
Requires-Python: ==3.10.*
Classifier: Programming Language :: Python :: 3
Classifier: Programming Language :: Python :: 3.10
Requires-Dist: inquirerpy (>=0.3.4,<0.4.0)
Requires-Dist: numpy (>=1.26.4,<2.0.0)
Requires-Dist: pandas (>=2.2.1,<3.0.0)
Requires-Dist: pysmile (>=2.2.0,<3.0.0)
Requires-Dist: typer[all] (>=0.9.0,<0.10.0)
